drift_protocol/__init__.py
drift_protocol/common/__init__.py
drift_protocol/common/data_payload_pb2.py
drift_protocol/common/drift_package_pb2.py
drift_protocol/common/status_code_pb2.py
drift_protocol/meta/__init__.py
drift_protocol/meta/meta_info_pb2.py
drift_protocol/trigger_service/__init__.py
drift_protocol/trigger_service/interval_trigger_message_pb2.py
drift_protocol/trigger_service/trigger_message_pb2.py
drift_protocol-0.6.0.dist-info/METADATA
drift_protocol-0.6.0.dist-info/WHEEL
drift_protocol-0.6.0.dist-info/top_level.txt
drift_protocol-0.6.0.dist-info/RECORD
