Metadata-Version: 2.1
Name: drift-protocol
Version: 0.6.0
Summary: Protobuf Libraries to encode message in Drift infrastructure
Home-page: https://github.com/panda-official/DriftProtocol/
Author: PANDA, GmbH
Author-email: info@panda.technology
License: UNKNOWN
Platform: UNKNOWN
Requires-Python: >=3.7
Requires-Dist: protobuf (<=3.20.3,>=3.12.4)
